{
  "scattered_image": "output_dataset/image_0045_people/scattered.png",
  "canvas_size": [
    1800,
    1800
  ],
  "pieces_positions": [
    {
      "piece_id": 0,
      "x": 1233,
      "y": 169,
      "rotation": -6.3192627852853125,
      "width": 332,
      "height": 332
    },
    {
      "piece_id": 1,
      "x": 1148,
      "y": 785,
      "rotation": -13.493680411967368,
      "width": 362,
      "height": 362
    },
    {
      "piece_id": 2,
      "x": 281,
      "y": 319,
      "rotation": 11.176691812096678,
      "width": 354,
      "height": 354
    },
    {
      "piece_id": 3,
      "x": 668,
      "y": 1298,
      "rotation": 7.967356026300806,
      "width": 340,
      "height": 340
    },
    {
      "piece_id": 4,
      "x": 763,
      "y": 646,
      "rotation": -14.568819713269926,
      "width": 366,
      "height": 366
    },
    {
      "piece_id": 5,
      "x": 705,
      "y": 184,
      "rotation": -10.679270591852479,
      "width": 352,
      "height": 352
    },
    {
      "piece_id": 6,
      "x": 1013,
      "y": 1401,
      "rotation": 2.722261916669048,
      "width": 314,
      "height": 314
    },
    {
      "piece_id": 7,
      "x": 603,
      "y": 975,
      "rotation": 1.8086151351365771,
      "width": 310,
      "height": 310
    },
    {
      "piece_id": 8,
      "x": 62,
      "y": 1209,
      "rotation": 0.22307724496980974,
      "width": 302,
      "height": 302
    }
  ]
}