{
  "scattered_image": "output_dataset/image_0057_abstract/scattered.png",
  "canvas_size": [
    1800,
    1800
  ],
  "pieces_positions": [
    {
      "piece_id": 0,
      "x": 228,
      "y": 298,
      "rotation": -12.429625434428374,
      "width": 358,
      "height": 358
    },
    {
      "piece_id": 1,
      "x": 1373,
      "y": 710,
      "rotation": 3.6569382677771713,
      "width": 320,
      "height": 320
    },
    {
      "piece_id": 2,
      "x": 788,
      "y": 1388,
      "rotation": -8.648502761455017,
      "width": 342,
      "height": 342
    },
    {
      "piece_id": 3,
      "x": 258,
      "y": 733,
      "rotation": 7.969912821771402,
      "width": 340,
      "height": 340
    },
    {
      "piece_id": 4,
      "x": 1356,
      "y": 1278,
      "rotation": -4.907627594104538,
      "width": 326,
      "height": 326
    },
    {
      "piece_id": 5,
      "x": 747,
      "y": 411,
      "rotation": -12.363869495048386,
      "width": 358,
      "height": 358
    },
    {
      "piece_id": 6,
      "x": 836,
      "y": 994,
      "rotation": 9.919288673082622,
      "width": 348,
      "height": 348
    },
    {
      "piece_id": 7,
      "x": 215,
      "y": 1350,
      "rotation": -14.131831950622113,
      "width": 366,
      "height": 366
    },
    {
      "piece_id": 8,
      "x": 1330,
      "y": 166,
      "rotation": -1.9808515354211575,
      "width": 312,
      "height": 312
    }
  ]
}