{
  "scattered_image": "output_dataset/image_0036_technology/scattered.png",
  "canvas_size": [
    1800,
    1800
  ],
  "pieces_positions": [
    {
      "piece_id": 0,
      "x": 1296,
      "y": 1319,
      "rotation": -13.887576216952585,
      "width": 364,
      "height": 364
    },
    {
      "piece_id": 1,
      "x": 156,
      "y": 188,
      "rotation": 14.757545075736822,
      "width": 368,
      "height": 368
    },
    {
      "piece_id": 2,
      "x": 831,
      "y": 631,
      "rotation": -12.275323919928148,
      "width": 358,
      "height": 358
    },
    {
      "piece_id": 3,
      "x": 580,
      "y": 1061,
      "rotation": -7.8443126301387185,
      "width": 340,
      "height": 340
    },
    {
      "piece_id": 4,
      "x": 54,
      "y": 703,
      "rotation": -1.9295677615607438,
      "width": 310,
      "height": 310
    },
    {
      "piece_id": 5,
      "x": 1362,
      "y": 401,
      "rotation": -14.256935781752718,
      "width": 366,
      "height": 366
    },
    {
      "piece_id": 6,
      "x": 1304,
      "y": 834,
      "rotation": -0.31450659067047226,
      "width": 302,
      "height": 302
    },
    {
      "piece_id": 7,
      "x": 908,
      "y": 138,
      "rotation": 11.375014979753601,
      "width": 354,
      "height": 354
    },
    {
      "piece_id": 8,
      "x": 794,
      "y": 1412,
      "rotation": -4.894142059660659,
      "width": 326,
      "height": 326
    }
  ]
}